evmoswallet/__init__.py
evmoswallet/converter/__init__.py
evmoswallet/converter/bech32.py
evmoswallet/crypto/__init__.py
evmoswallet/crypto/ecdsa.py
evmoswallet/crypto/ecdsa_base.py
evmoswallet/crypto/ecdsa_openssl.py
evmoswallet/crypto/ecdsa_python.py
evmoswallet/crypto/openssl.py
evmoswallet/crypto/utils.py
evmoswallet/eth/__init__.py
evmoswallet/eth/ethereum.py
tests/__init__.py
tests/converter/__init__.py
tests/converter/test_converter.py
tests/wallet/__init__.py
tests/wallet/test_wallet.py
evmoswallet-1.0.4.dist-info/LICENSE
evmoswallet-1.0.4.dist-info/METADATA
evmoswallet-1.0.4.dist-info/WHEEL
evmoswallet-1.0.4.dist-info/top_level.txt
evmoswallet-1.0.4.dist-info/RECORD
