Metadata-Version: 2.1
Name: evmoswallet
Version: 1.0.4
Summary: Evmos wallet utils.
Home-page: https://github.com/hanchon-live/evmoswallet
Author: Hanchon
Author-email: guillermo.paoletti@gmail.com
License: MIT
Platform: UNKNOWN
Classifier: License :: OSI Approved :: MIT License
Classifier: Operating System :: OS Independent
Classifier: Programming Language :: Python :: 3
Classifier: Programming Language :: Python :: 3 :: Only
Classifier: Programming Language :: Python :: 3.6
Classifier: Programming Language :: Python :: 3.7
Classifier: Programming Language :: Python :: 3.8
Classifier: Programming Language :: Python :: 3.9
Classifier: Programming Language :: Python :: 3.10
Requires-Python: >=3.6
Requires-Dist: base58 (==2.1.0)
Requires-Dist: coincurve (==15.0.1)
Requires-Dist: mnemonic (==0.20)
Requires-Dist: pycryptodomex (==3.11.0)
